{"config_hash": "249d321f4b931ef3db355ec01afdc9eab12175f2e8454955fde05526c0090572", "end_ts_ms": 1769903999999, "engine_mode": "BACKTEST", "git_sha": "36e1ace6356d5aa190c062528e586e93ee1f779d", "interval": "15m", "performance_summary": {"max_drawdown": -0.19412997955255887, "sharpe": 1.6439005615336721, "total_return": 1.952571901270682, "total_trades": 3730}, "quality_verdict": "DEGRADED", "report_generated_at": "2026-03-14T12:06:56.837611Z", "report_schema_version": "report_v1", "run_id": "RSI-ADX-GATEWAY-FRACTIONAL20260314T120457Z", "start_ts_ms": 1679937299999, "strategy_name": "<unnamed>", "symbol": "BTCUSDT", "total_fills": 3892, "total_steps": 99964, "warning_count": {"critical": 0, "info": 0, "warning": 364}}